Workbook

Sheet Summary
A1: Demo Company Payroll – This Month Solution
A2: Days in payroll month | B2: 30 | D2: Total gross pay | E2: =ROUND(SUM(Payroll_Run!Z3:Z13),2) -> 63377.77 | G2: Corrected arithmetic: 50% deductions = 50% net pay; 55% deductions = 45% net pay.
A3: Income tax rate | B3: 0.35 | D3: Income tax | E3: =ROUND(SUM(Payroll_Run!AA3:AA13),2) -> 22182.22 | G3: Signing bonus included only for Tom Tinker (£1,000). David confirmed no other bonuses this month.
A4: National Insurance rate | B4: 0.1 | D4: National Insurance | E4: =ROUND(SUM(Payroll_Run!AB3:AB13),2) -> 6337.77 | G4: Student loan evidence is only explicit on the P45s: Terry = Yes, Tom = No. Existing employees assumed No because no student-loan source data was provided.
A5: Pension rate | B5: 0.05 | D5: Pension | E5: =ROUND(SUM(Payroll_Run!AC3:AC13),2) -> 3168.89 | G5: Tom Tinker is pro-rated using a 30-day month and 23 days worked (started on the 8th).
A6: Student loan rate | B6: 0.05 | D6: Student loan | E6: =ROUND(SUM(Payroll_Run!AD3:AD13),2) -> 208.33 | G6: Terry's address in payroll uses Gemma's updated address rather than the old P45 address.
D7: Total deductions | E7: =ROUND(SUM(E3:E6),2) -> 31897.21 | G7: P45 previous pay/tax are logged for completeness but not used in the simplified deduction rules.
D8: Total net pay | E8: =ROUND(SUM(Payroll_Run!AE3:AE13),2) -> 31480.56
A9: Employee Net Pay Summary
A10: Employee | B10: Gross This Month | C10: Student Loan? | D10: Net Pay
A11: =Payroll_Run!A3&" "&Payroll_Run!B3 -> David Watkins | B11: =Payroll_Run!Z3 -> 7083.33 | C11: =Payroll_Run!R3 -> No | D11: =Payroll_Run!AE3 -> 3541.66
A12: =Payroll_Run!A4&" "&Payroll_Run!B4 -> Gemma Tompson | B12: =Payroll_Run!Z4 -> 4583.33 | C12: =Payroll_Run!R4 -> No | D12: =Payroll_Run!AE4 -> 2291.66
A13: =Payroll_Run!A5&" "&Payroll_Run!B5 -> Olivia Newton | B13: =Payroll_Run!Z5 -> 4166.67 | C13: =Payroll_Run!R5 -> No | D13: =Payroll_Run!AE5 -> 2083.34
A14: =Payroll_Run!A6&" "&Payroll_Run!B6 -> James Telford | B14: =Payroll_Run!Z6 -> 5000 | C14: =Payroll_Run!R6 -> No | D14: =Payroll_Run!AE6 -> 2500
A15: =Payroll_Run!A7&" "&Payroll_Run!B7 -> Judy Murray | B15: =Payroll_Run!Z7 -> 9166.67 | C15: =Payroll_Run!R7 -> No | D15: =Payroll_Run!AE7 -> 4583.34
A16: =Payroll_Run!A8&" "&Payroll_Run!B8 -> Gemma Collins | B16: =Payroll_Run!Z8 -> 2333.33 | C16: =Payroll_Run!R8 -> No | D16: =Payroll_Run!AE8 -> 1166.66
A17: =Payroll_Run!A9&" "&Payroll_Run!B9 -> Tom Cruze | B17: =Payroll_Run!Z9 -> 5833.33 | C17: =Payroll_Run!R9 -> No | D17: =Payroll_Run!AE9 -> 2916.66
A18: =Payroll_Run!A10&" "&Payroll_Run!B10 -> Colin Naylor | B18: =Payroll_Run!Z10 -> 9666.67 | C18: =Payroll_Run!R10 -> No | D18: =Payroll_Run!AE10 -> 4833.34
A19: =Payroll_Run!A11&" "&Payroll_Run!B11 -> Jenny Holland | B19: =Payroll_Run!Z11 -> 8333.33 | C19: =Payroll_Run!R11 -> No | D19: =Payroll_Run!AE11 -> 4166.66
A20: =Payroll_Run!A12&" "&Payroll_Run!B12 -> Terry Tucker | B20: =Payroll_Run!Z12 -> 4166.67 | C20: =Payroll_Run!R12 -> Yes | D20: =Payroll_Run!AE12 -> 1875.01
A21: =Payroll_Run!A13&" "&Payroll_Run!B13 -> Tom Tinker | B21: =Payroll_Run!Z13 -> 3044.44 | C21: =Payroll_Run!R13 -> No | D21: =Payroll_Run!AE13 -> 1522.23

Sheet Payroll_Run
A1: Payroll Working File – Updated for This Month
A2: First Name | B2: Surname | C2: Start Date | D2: NI Number | E2: Title | F2: Gender | G2: Date of Birth | H2: Address 1 | I2: Address 2 | J2: Address 3 | K2: Postcode | L2: Email | M2: Phone | N2: Tax Code | O2: W1/M1 Basis | P2: NI Table | Q2: Director? | R2: Student Loan? | S2: Postgrad Loan | T2: Payment Freq | U2: Annual Pay Rate | V2: Base Monthly Gross | W2: Worked Days This Month | X2: Proration Factor | Y2: Bonus This Month | Z2: Gross This Month | AA2: Income Tax | AB2: NI | AC2: Pension | AD2: Student Loan | AE2: Net Pay | AF2: P45 Prior Pay | AG2: P45 Prior Tax | AH2: Source / Notes
A3: David | B3: Watkins | C3: 19/10/2023 | D3: AB6981536C | E3: Mr | F3: Male | G3: 1989-06-15 | H3: 11D | I3: 33 North Road | J3: Glasgow | K3: LS1 1AA | L3: takehometasks+davidwatkins@novabook.com | M3: 447782950110 | N3: K877 | O3: Yes | P3: A | Q3: Yes | R3: No | S3: No | T3: Monthly | U3: 85000 | V3: =ROUND(U3/12,2) -> 7083.33 | W3: 30 | X3: =W3/Summary!$B$2 -> 1 | Y3: 0 | Z3: =ROUND((U3/12)*X3+Y3,2) -> 7083.33 | AA3: =ROUND(Z3*Summary!$B$3,2) -> 2479.17 | AB3: =ROUND(Z3*Summary!$B$4,2) -> 708.33 | AC3: =ROUND(Z3*Summary!$B$5,2) -> 354.17 | AD3: =IF(R3="Yes",ROUND(Z3*Summary!$B$6,2),0) -> 0 | AE3: =ROUND(Z3-AA3-AB3-AC3-AD3,2) -> 3541.66 | AH3: Existing employee. £1,000 bonus from last-month file removed per David email.
A4: Gemma | B4: Tompson | C4: 25/08/2023 | D4: OP7103256C | E4: Miss | F4: Female | G4: 2002-01-07 | H4: Flat 7 | I4: 33 North Road | J4: Edinburgh | K4: S1 1AA | L4: gemma.tompson@demo-company.io | M4: 447243281470 | N4: 1257L | O4: No | P4: A | Q4: No | R4: No | S4: No | T4: Monthly | U4: 55000 | V4: =ROUND(U4/12,2) -> 4583.33 | W4: 30 | X4: =W4/Summary!$B$2 -> 1 | Y4: 0 | Z4: =ROUND((U4/12)*X4+Y4,2) -> 4583.33 | AA4: =ROUND(Z4*Summary!$B$3,2) -> 1604.17 | AB4: =ROUND(Z4*Summary!$B$4,2) -> 458.33 | AC4: =ROUND(Z4*Summary!$B$5,2) -> 229.17 | AD4: =IF(R4="Yes",ROUND(Z4*Summary!$B$6,2),0) -> 0 | AE4: =ROUND(Z4-AA4-AB4-AC4-AD4,2) -> 2291.66 | AH4: Existing employee.
A5: Olivia | B5: Newton | C5: 07/09/2022 | D5: CD9874380C | E5: Mr | F5: Female | G5: 2002-11-21 | H5: 12A | I5: 6 Maple Drive | J5: Cardiff | K5: B1 1AA | L5: olivia.newton@demo-company.io | M5: 447611567429 | N5: 1257L | O5: No | P5: A | Q5: No | R5: No | S5: No | T5: Monthly | U5: 50000 | V5: =ROUND(U5/12,2) -> 4166.67 | W5: 30 | X5: =W5/Summary!$B$2 -> 1 | Y5: 0 | Z5: =ROUND((U5/12)*X5+Y5,2) -> 4166.67 | AA5: =ROUND(Z5*Summary!$B$3,2) -> 1458.33 | AB5: =ROUND(Z5*Summary!$B$4,2) -> 416.67 | AC5: =ROUND(Z5*Summary!$B$5,2) -> 208.33 | AD5: =IF(R5="Yes",ROUND(Z5*Summary!$B$6,2),0) -> 0 | AE5: =ROUND(Z5-AA5-AB5-AC5-AD5,2) -> 2083.34 | AH5: Existing employee.
A6: James | B6: Telford | C6: 20/06/2023 | D6: MN9935842C | E6: Mr | F6: Male | G6: 1997-09-01 | H6: Apartment 205 | I6: 6 Maple Drive | J6: Bristol | K6: M1 1AE | L6: james.telford@demo-company.io | M6: 447426615520 | N6: 1257L | O6: No | P6: A | Q6: Yes | R6: No | S6: No | T6: Monthly | U6: 60000 | V6: =ROUND(U6/12,2) -> 5000 | W6: 30 | X6: =W6/Summary!$B$2 -> 1 | Y6: 0 | Z6: =ROUND((U6/12)*X6+Y6,2) -> 5000 | AA6: =ROUND(Z6*Summary!$B$3,2) -> 1750 | AB6: =ROUND(Z6*Summary!$B$4,2) -> 500 | AC6: =ROUND(Z6*Summary!$B$5,2) -> 250 | AD6: =IF(R6="Yes",ROUND(Z6*Summary!$B$6,2),0) -> 0 | AE6: =ROUND(Z6-AA6-AB6-AC6-AD6,2) -> 2500 | AH6: Existing employee.
A7: Judy | B7: Murray | C7: 08/08/2023 | D7: OP4261042C | E7: Mr | F7: Female | G7: 1991-08-05 | H7: 1.2 Regent House | I7: 8 East Lane | J7: Glasgow | K7: L1 1AE | L7: judy.murray@demo-company.io | M7: 447557497082 | N7: 897T | O7: No | P7: A | Q7: No | R7: No | S7: No | T7: Monthly | U7: 110000 | V7: =ROUND(U7/12,2) -> 9166.67 | W7: 30 | X7: =W7/Summary!$B$2 -> 1 | Y7: 0 | Z7: =ROUND((U7/12)*X7+Y7,2) -> 9166.67 | AA7: =ROUND(Z7*Summary!$B$3,2) -> 3208.33 | AB7: =ROUND(Z7*Summary!$B$4,2) -> 916.67 | AC7: =ROUND(Z7*Summary!$B$5,2) -> 458.33 | AD7: =IF(R7="Yes",ROUND(Z7*Summary!$B$6,2),0) -> 0 | AE7: =ROUND(Z7-AA7-AB7-AC7-AD7,2) -> 4583.34 | AH7: Existing employee.
A8: Gemma | B8: Collins | C8: 24/11/2022 | D8: IJ9828043C | E8: Miss | F8: Female | G8: 1996-05-05 | H8: Suite 4 | I8: 10 High Street | J8: Glasgow | K8: B1 1AA | L8: takehometasks+gemmacollins@novabook.com | M8: 447292234345 | N8: 1257L | O8: No | P8: A | Q8: No | R8: No | S8: No | T8: Monthly | U8: 28000 | V8: =ROUND(U8/12,2) -> 2333.33 | W8: 30 | X8: =W8/Summary!$B$2 -> 1 | Y8: 0 | Z8: =ROUND((U8/12)*X8+Y8,2) -> 2333.33 | AA8: =ROUND(Z8*Summary!$B$3,2) -> 816.67 | AB8: =ROUND(Z8*Summary!$B$4,2) -> 233.33 | AC8: =ROUND(Z8*Summary!$B$5,2) -> 116.67 | AD8: =IF(R8="Yes",ROUND(Z8*Summary!$B$6,2),0) -> 0 | AE8: =ROUND(Z8-AA8-AB8-AC8-AD8,2) -> 1166.66 | AH8: Office manager email received with new-joiner details and P45 attachments.
A9: Tom | B9: Cruze | C9: 25/01/2024 | D9: KL0740250C | E9: Miss | F9: Male | G9: 1997-08-23 | H9: Flat 7 | I9: 14 Elm Street | J9: Manchester | K9: B1 1AA | L9: tom.cruze@demo-company.io | M9: 447136816120 | N9: K422 | O9: Yes | P9: A | Q9: No | R9: No | S9: No | T9: Monthly | U9: 70000 | V9: =ROUND(U9/12,2) -> 5833.33 | W9: 30 | X9: =W9/Summary!$B$2 -> 1 | Y9: 0 | Z9: =ROUND((U9/12)*X9+Y9,2) -> 5833.33 | AA9: =ROUND(Z9*Summary!$B$3,2) -> 2041.67 | AB9: =ROUND(Z9*Summary!$B$4,2) -> 583.33 | AC9: =ROUND(Z9*Summary!$B$5,2) -> 291.67 | AD9: =IF(R9="Yes",ROUND(Z9*Summary!$B$6,2),0) -> 0 | AE9: =ROUND(Z9-AA9-AB9-AC9-AD9,2) -> 2916.66 | AH9: Existing employee. £2,000 bonus from last-month file removed per David email.
A10: Colin | B10: Naylor | C10: 02/01/2024 | D10: MN1081847C | E10: Mr | F10: Male | G10: 1993-08-19 | H10: Penthouse 8 | I10: 9 West Avenue | J10: Manchester | K10: L1 1AE | L10: colin.naylor@demo-company.io | M10: 447452987908 | N10: 1257L | O10: No | P10: A | Q10: No | R10: No | S10: No | T10: Monthly | U10: 116000 | V10: =ROUND(U10/12,2) -> 9666.67 | W10: 30 | X10: =W10/Summary!$B$2 -> 1 | Y10: 0 | Z10: =ROUND((U10/12)*X10+Y10,2) -> 9666.67 | AA10: =ROUND(Z10*Summary!$B$3,2) -> 3383.33 | AB10: =ROUND(Z10*Summary!$B$4,2) -> 966.67 | AC10: =ROUND(Z10*Summary!$B$5,2) -> 483.33 | AD10: =IF(R10="Yes",ROUND(Z10*Summary!$B$6,2),0) -> 0 | AE10: =ROUND(Z10-AA10-AB10-AC10-AD10,2) -> 4833.34 | AH10: Existing employee.
A11: Jenny | B11: Holland | C11: 27/03/2023 | D11: AB0014612C | E11: Mr | F11: Female | G11: 1989-12-19 | H11: 3rd Floor | I11: 5 Broadway | J11: Edinburgh | K11: SW1A 1AA | L11: jenny.holland@demo-company.io | M11: 447257112727 | N11: 1257L | O11: Yes | P11: A | Q11: No | R11: No | S11: No | T11: Monthly | U11: 100000 | V11: =ROUND(U11/12,2) -> 8333.33 | W11: 30 | X11: =W11/Summary!$B$2 -> 1 | Y11: 0 | Z11: =ROUND((U11/12)*X11+Y11,2) -> 8333.33 | AA11: =ROUND(Z11*Summary!$B$3,2) -> 2916.67 | AB11: =ROUND(Z11*Summary!$B$4,2) -> 833.33 | AC11: =ROUND(Z11*Summary!$B$5,2) -> 416.67 | AD11: =IF(R11="Yes",ROUND(Z11*Summary!$B$6,2),0) -> 0 | AE11: =ROUND(Z11-AA11-AB11-AC11-AD11,2) -> 4166.66 | AH11: Existing employee.
A12: Terry | B12: Tucker | C12: 1st of month | D12: HG7898764 | E12: Mr | F12: Male | G12: 1993-05-19 | H12: 123 Buckingham Palace Road | I12: London | K12: SW1 9JU | L12: takehometasks+terrytucker@novabook.com | M12: 07674822929 | N12: 1257L | O12: Yes | P12: A | Q12: No | R12: Yes | S12: No | T12: Monthly | U12: 50000 | V12: =ROUND(U12/12,2) -> 4166.67 | W12: 30 | X12: =W12/Summary!$B$2 -> 1 | Y12: 0 | Z12: =ROUND((U12/12)*X12+Y12,2) -> 4166.67 | AA12: =ROUND(Z12*Summary!$B$3,2) -> 1458.33 | AB12: =ROUND(Z12*Summary!$B$4,2) -> 416.67 | AC12: =ROUND(Z12*Summary!$B$5,2) -> 208.33 | AD12: =IF(R12="Yes",ROUND(Z12*Summary!$B$6,2),0) -> 208.33 | AE12: =ROUND(Z12-AA12-AB12-AC12-AD12,2) -> 1875.01 | AF12: 2000 | AG12: 400 | AH12: New joiner. P45 shows student-loan deductions due and prior pay/tax of £2,000/£400. Address updated from Gemma email.
A13: Tom | B13: Tinker | C13: 8th of month | D13: JP3238864 | E13: Mr | F13: Male | G13: 1997-04-03 | H13: 31 Station Road | I13: Bow Brickhill | J13: Milton Keynes | K13: MK17 9JU | L13: takehometasks+tomtinker@novabook.com | M13: 07858394406 | N13: 1257L | O13: No | P13: A | Q13: No | R13: No | S13: No | T13: Monthly | U13: 32000 | V13: =ROUND(U13/12,2) -> 2666.67 | W13: 23 | X13: =W13/Summary!$B$2 -> 0.76666667 | Y13: 1000 | Z13: =ROUND((U13/12)*X13+Y13,2) -> 3044.44 | AA13: =ROUND(Z13*Summary!$B$3,2) -> 1065.55 | AB13: =ROUND(Z13*Summary!$B$4,2) -> 304.44 | AC13: =ROUND(Z13*Summary!$B$5,2) -> 152.22 | AD13: =IF(R13="Yes",ROUND(Z13*Summary!$B$6,2),0) -> 0 | AE13: =ROUND(Z13-AA13-AB13-AC13-AD13,2) -> 1522.23 | AF13: 3000 | AG13: 750 | AH13: New joiner. P45 shows no student loan. £1,000 signing bonus included per David email.

Sheet Outputs
A1: Employee | B1: Gross | C1: Tax | D1: NI | E1: Pension | F1: Student Loan | G1: Net
A2: =Payroll_Run!A3&" "&Payroll_Run!B3 -> David Watkins | B2: =Payroll_Run!Z3 -> 7083.33 | C2: =Payroll_Run!AA3 -> 2479.17 | D2: =Payroll_Run!AB3 -> 708.33 | E2: =Payroll_Run!AC3 -> 354.17 | F2: =Payroll_Run!AD3 -> 0 | G2: =Payroll_Run!AE3 -> 3541.66
A3: =Payroll_Run!A4&" "&Payroll_Run!B4 -> Gemma Tompson | B3: =Payroll_Run!Z4 -> 4583.33 | C3: =Payroll_Run!AA4 -> 1604.17 | D3: =Payroll_Run!AB4 -> 458.33 | E3: =Payroll_Run!AC4 -> 229.17 | F3: =Payroll_Run!AD4 -> 0 | G3: =Payroll_Run!AE4 -> 2291.66
A4: =Payroll_Run!A5&" "&Payroll_Run!B5 -> Olivia Newton | B4: =Payroll_Run!Z5 -> 4166.67 | C4: =Payroll_Run!AA5 -> 1458.33 | D4: =Payroll_Run!AB5 -> 416.67 | E4: =Payroll_Run!AC5 -> 208.33 | F4: =Payroll_Run!AD5 -> 0 | G4: =Payroll_Run!AE5 -> 2083.34
A5: =Payroll_Run!A6&" "&Payroll_Run!B6 -> James Telford | B5: =Payroll_Run!Z6 -> 5000 | C5: =Payroll_Run!AA6 -> 1750 | D5: =Payroll_Run!AB6 -> 500 | E5: =Payroll_Run!AC6 -> 250 | F5: =Payroll_Run!AD6 -> 0 | G5: =Payroll_Run!AE6 -> 2500
A6: =Payroll_Run!A7&" "&Payroll_Run!B7 -> Judy Murray | B6: =Payroll_Run!Z7 -> 9166.67 | C6: =Payroll_Run!AA7 -> 3208.33 | D6: =Payroll_Run!AB7 -> 916.67 | E6: =Payroll_Run!AC7 -> 458.33 | F6: =Payroll_Run!AD7 -> 0 | G6: =Payroll_Run!AE7 -> 4583.34
A7: =Payroll_Run!A8&" "&Payroll_Run!B8 -> Gemma Collins | B7: =Payroll_Run!Z8 -> 2333.33 | C7: =Payroll_Run!AA8 -> 816.67 | D7: =Payroll_Run!AB8 -> 233.33 | E7: =Payroll_Run!AC8 -> 116.67 | F7: =Payroll_Run!AD8 -> 0 | G7: =Payroll_Run!AE8 -> 1166.66
A8: =Payroll_Run!A9&" "&Payroll_Run!B9 -> Tom Cruze | B8: =Payroll_Run!Z9 -> 5833.33 | C8: =Payroll_Run!AA9 -> 2041.67 | D8: =Payroll_Run!AB9 -> 583.33 | E8: =Payroll_Run!AC9 -> 291.67 | F8: =Payroll_Run!AD9 -> 0 | G8: =Payroll_Run!AE9 -> 2916.66
A9: =Payroll_Run!A10&" "&Payroll_Run!B10 -> Colin Naylor | B9: =Payroll_Run!Z10 -> 9666.67 | C9: =Payroll_Run!AA10 -> 3383.33 | D9: =Payroll_Run!AB10 -> 966.67 | E9: =Payroll_Run!AC10 -> 483.33 | F9: =Payroll_Run!AD10 -> 0 | G9: =Payroll_Run!AE10 -> 4833.34
A10: =Payroll_Run!A11&" "&Payroll_Run!B11 -> Jenny Holland | B10: =Payroll_Run!Z11 -> 8333.33 | C10: =Payroll_Run!AA11 -> 2916.67 | D10: =Payroll_Run!AB11 -> 833.33 | E10: =Payroll_Run!AC11 -> 416.67 | F10: =Payroll_Run!AD11 -> 0 | G10: =Payroll_Run!AE11 -> 4166.66
A11: =Payroll_Run!A12&" "&Payroll_Run!B12 -> Terry Tucker | B11: =Payroll_Run!Z12 -> 4166.67 | C11: =Payroll_Run!AA12 -> 1458.33 | D11: =Payroll_Run!AB12 -> 416.67 | E11: =Payroll_Run!AC12 -> 208.33 | F11: =Payroll_Run!AD12 -> 208.33 | G11: =Payroll_Run!AE12 -> 1875.01
A12: =Payroll_Run!A13&" "&Payroll_Run!B13 -> Tom Tinker | B12: =Payroll_Run!Z13 -> 3044.44 | C12: =Payroll_Run!AA13 -> 1065.55 | D12: =Payroll_Run!AB13 -> 304.44 | E12: =Payroll_Run!AC13 -> 152.22 | F12: =Payroll_Run!AD13 -> 0 | G12: =Payroll_Run!AE13 -> 1522.23
A16: Gross pay | B16: =Payroll_Run!Z12 -> 4166.67
A17: Income tax | B17: =Payroll_Run!AA12 -> 1458.33
A18: National Insurance | B18: =Payroll_Run!AB12 -> 416.67
A19: Pension | B19: =Payroll_Run!AC12 -> 208.33
A20: Student loan | B20: =Payroll_Run!AD12 -> 208.33
A21: Net pay | B21: =Payroll_Run!AE12 -> 1875.01
A23: Payslip – Tom Tinker
A24: Gross pay | B24: =Payroll_Run!Z13 -> 3044.44
A25: Income tax | B25: =Payroll_Run!AA13 -> 1065.55
A26: National Insurance | B26: =Payroll_Run!AB13 -> 304.44
A27: Pension | B27: =Payroll_Run!AC13 -> 152.22
A28: Student loan | B28: =Payroll_Run!AD13 -> 0
A29: Net pay | B29: =Payroll_Run!AE13 -> 1522.23

Sheet Employee_Master_Data
A1: Employee ID | B1: First Name | C1: Surname | D1: Start Date | E1: NI Number | F1: Title | G1: Gender | H1: Date of Birth | I1: Address 1 | J1: Address 2 | K1: Address 3 | L1: Postcode | M1: Email | N1: Phone | O1: Tax Code | P1: W1/M1 Basis | Q1: NI Table | R1: Director? | S1: Student Loan? | T1: Postgrad Loan | U1: Payment Freq | V1: Annual Pay Rate
A2: EMP001 | B2: David | C2: Watkins | D2: 2023-10-19 | E2: AB6981536C | F2: Mr | G2: Male | H2: 1989-06-15 | I2: 11D | J2: 33 North Road | K2: Glasgow | L2: LS1 1AA | M2: takehometasks+davidwatkins@novabook.com | N2: 447782950110 | O2: K877 | P2: Yes | Q2: A | R2: Yes | S2: No | T2: No | U2: Monthly | V2: 85000
A3: EMP002 | B3: Gemma | C3: Tompson | D3: 2023-08-25 | E3: OP7103256C | F3: Miss | G3: Female | H3: 2002-01-07 | I3: Flat 7 | J3: 33 North Road | K3: Edinburgh | L3: S1 1AA | M3: gemma.tompson@demo-company.io | N3: 447243281470 | O3: 1257L | P3: No | Q3: A | R3: No | S3: No | T3: No | U3: Monthly | V3: 55000
A4: EMP003 | B4: Olivia | C4: Newton | D4: 2022-09-07 | E4: CD9874380C | F4: Mx | G4: Female | H4: 2002-11-21 | I4: 12A | J4: 6 Maple Drive | K4: Cardiff | L4: B1 1AA | M4: olivia.newton@demo-company.io | N4: 447611567429 | O4: 1257L | P4: No | Q4: A | R4: No | S4: No | T4: No | U4: Monthly | V4: 50000
A5: EMP004 | B5: James | C5: Telford | D5: 2023-06-20 | E5: MN9935842C | F5: Mr | G5: Male | H5: 1997-09-01 | I5: Apartment 205 | J5: 6 Maple Drive | K5: Bristol | L5: M1 1AE | M5: james.telford@demo-company.io | N5: 447426615520 | O5: 1257L | P5: No | Q5: A | R5: Yes | S5: No | T5: No | U5: Monthly | V5: 60000
A6: EMP005 | B6: Judy | C6: Murray | D6: 2023-08-08 | E6: OP4261042C | F6: Ms | G6: Female | H6: 1991-08-05 | I6: 1.2 Regent House | J6: 8 East Lane | K6: Glasgow | L6: L1 1AE | M6: judy.murray@demo-company.io | N6: 447557497082 | O6: 897T | P6: No | Q6: A | R6: No | S6: No | T6: No | U6: Monthly | V6: 110000
A7: EMP006 | B7: Gemma | C7: Collins | D7: 2022-11-24 | E7: IJ9828043C | F7: Miss | G7: Female | H7: 1996-05-05 | I7: Suite 4 | J7: 10 High Street | K7: Glasgow | L7: B1 1AA | M7: takehometasks+gemmacollins@novabook.com | N7: 447292234345 | O7: 1257L | P7: No | Q7: A | R7: No | S7: No | T7: No | U7: Monthly | V7: 28000
A8: EMP007 | B8: Tom | C8: Cruze | D8: 2024-01-25 | E8: KL0740250C | F8: Mr | G8: Male | H8: 1997-08-23 | I8: Flat 7 | J8: 14 Elm Street | K8: Manchester | L8: B1 1AA | M8: tom.cruze@demo-company.io | N8: 447136816120 | O8: K422 | P8: Yes | Q8: A | R8: No | S8: No | T8: No | U8: Monthly | V8: 70000
A9: EMP008 | B9: Colin | C9: Naylor | D9: 2024-01-02 | E9: MN1081847C | F9: Mr | G9: Male | H9: 1993-08-19 | I9: Penthouse 8 | J9: 9 West Avenue | K9: Manchester | L9: L1 1AE | M9: colin.naylor@demo-company.io | N9: 447452987908 | O9: 1257L | P9: No | Q9: A | R9: No | S9: No | T9: No | U9: Monthly | V9: 116000
A10: EMP009 | B10: Jenny | C10: Holland | D10: 2023-03-27 | E10: AB0014612C | F10: Ms | G10: Female | H10: 1989-12-19 | I10: 3rd Floor | J10: 5 Broadway | K10: Edinburgh | L10: SW1A 1AA | M10: jenny.holland@demo-company.io | N10: 447257112727 | O10: 1257L | P10: Yes | Q10: A | R10: No | S10: No | T10: No | U10: Monthly | V10: 100000
A11: EMP010 | B11: Terry | C11: Tucker | D11: 2024-04-01 | E11: HG7898764 | F11: Mr | G11: Male | H11: 1993-05-19 | I11: 123 Buckingham Palace Road | J11: London | L11: SW1 9JU | M11: takehometasks+terrytucker@novabook.com | N11: 07674822929 | O11: 1257L | P11: Yes | Q11: A | R11: No | S11: Yes | T11: No | U11: Monthly | V11: 50000
A12: EMP011 | B12: Tom | C12: Tinker | D12: 2024-04-08 | E12: JP3238864 | F12: Mr | G12: Male | H12: 1997-04-03 | I12: 31 Station Road | J12: Bow Brickhill | K12: Milton Keynes | L12: MK17 9JU | M12: takehometasks+tomtinker@novabook.com | N12: 07858394406 | O12: 1257L | P12: No | Q12: A | R12: No | S12: No | T12: No | U12: Monthly | V12: 32000

Sheet Starter_P45_Data
A1: Employee ID | B1: Employee Name | C1: Starter Type | D1: P45 Received? | E1: Previous Employer | F1: Prev Taxable Pay YTD | G1: Prev Tax YTD | H1: Tax Code from P45 | I1: Student Loan from P45 | J1: Postgrad Loan from P45 | K1: Pension Start From | L1: Notes
A2: EMP010 | B2: Terry Tucker | C2: New joiner | D2: Yes | E2: Northbridge Services Ltd | F2: 18450 | G2: 2214 | H2: 1257L | I2: Yes | J2: No | K2: Start date | L2: Address updated to current London address before payroll processing
A3: EMP011 | B3: Tom Tinker | C3: New joiner | D3: Yes | E3: Marlowe Retail Group | F3: 9620 | G3: 748 | H3: 1257L | I3: No | J3: No | K3: Start date | L3: P45 used to confirm tax code; signing bonus approved separately

Sheet Monthly_Changes_Data
A1: Payroll Month | B1: Employee ID | C1: Employee Name | D1: Change Type | E1: Worked Days | F1: Payroll Days | G1: Proration Factor | H1: Base Monthly Gross | I1: Adjustment / Bonus | J1: Gross This Month | K1: Approval / Source Note
A2: 2024-04 | B2: EMP001 | C2: David Watkins | D2: No change | E2: 30 | F2: 30 | G2: 1 | H2: 7083.33 | I2: 0 | J2: 7083.33 | K2: Included in normal monthly payroll run
A3: 2024-04 | B3: EMP002 | C3: Gemma Tompson | D3: No change | E3: 30 | F3: 30 | G3: 1 | H3: 4583.33 | I3: 0 | J3: 4583.33 | K3: Included in normal monthly payroll run
A4: 2024-04 | B4: EMP003 | C4: Olivia Newton | D4: No change | E4: 30 | F4: 30 | G4: 1 | H4: 4166.67 | I4: 0 | J4: 4166.67 | K4: Included in normal monthly payroll run
A5: 2024-04 | B5: EMP004 | C5: James Telford | D5: No change | E5: 30 | F5: 30 | G5: 1 | H5: 5000 | I5: 0 | J5: 5000 | K5: Included in normal monthly payroll run
A6: 2024-04 | B6: EMP005 | C6: Judy Murray | D6: No change | E6: 30 | F6: 30 | G6: 1 | H6: 9166.67 | I6: 0 | J6: 9166.67 | K6: Included in normal monthly payroll run
A7: 2024-04 | B7: EMP006 | C7: Gemma Collins | D7: No change | E7: 30 | F7: 30 | G7: 1 | H7: 2333.33 | I7: 0 | J7: 2333.33 | K7: Included in normal monthly payroll run
A8: 2024-04 | B8: EMP007 | C8: Tom Cruze | D8: No change | E8: 30 | F8: 30 | G8: 1 | H8: 5833.33 | I8: 0 | J8: 5833.33 | K8: Included in normal monthly payroll run
A9: 2024-04 | B9: EMP008 | C9: Colin Naylor | D9: No change | E9: 30 | F9: 30 | G9: 1 | H9: 9666.67 | I9: 0 | J9: 9666.67 | K9: Included in normal monthly payroll run
A10: 2024-04 | B10: EMP009 | C10: Jenny Holland | D10: No change | E10: 30 | F10: 30 | G10: 1 | H10: 8333.33 | I10: 0 | J10: 8333.33 | K10: Included in normal monthly payroll run
A11: 2024-04 | B11: EMP010 | C11: Terry Tucker | D11: New starter - full month | E11: 30 | F11: 30 | G11: 1 | H11: 4166.67 | I11: 0 | J11: 4166.67 | K11: Joined on 1st of month; full monthly pay
A12: 2024-04 | B12: EMP011 | C12: Tom Tinker | D12: New starter - prorated + signing bonus | E12: 23 | F12: 30 | G12: 0.76666667 | H12: 2666.67 | I12: 1000 | J12: 3044.44 | K12: Started on 8th; 30-day proration plus approved signing bonus

Sheet Payroll_Assumptions_Data
A1: Assumption / Rate | B1: Value | C1: Explanation
A2: Payroll month | B2: 2024-04 | C2: Fake month used to support the workbook example
A3: Days in payroll month | B3: 30 | C3: Used for proration of mid-month starters
A4: Income tax rate | B4: 0.35 | C4: Simplified task rate applied to gross pay
A5: National Insurance rate | B5: 0.1 | C5: Simplified task rate applied to gross pay
A6: Pension rate | B6: 0.05 | C6: Simplified employee pension deduction rate
A7: Student loan rate | B7: 0.05 | C7: Applied only where student loan indicator is Yes
A8: Bonus handling | B8: All prior bonuses removed | C8: Only Tom Tinker's signing bonus is included this month
A9: Pension timing | B9: From start date | C9: New joiners assumed enrolled immediately
A10: Payroll frequency | B10: Monthly | C10: All staff processed on monthly cycle
